permutate/__init__.py
permutate/__main__.py
permutate/job_request_schema.py
permutate/job_response_schema.py
permutate/logger.py
permutate/main.py
permutate/runner.py
permutate/singleton.py
permutate/templates/job_result_template.html
permutate/workspace/plugin_test.yaml
permutate-0.0.10.dist-info/METADATA
permutate-0.0.10.dist-info/WHEEL
permutate-0.0.10.dist-info/entry_points.txt
permutate-0.0.10.dist-info/RECORD
