Metadata-Version: 2.1
Name: permutate
Version: 0.0.10
Summary: Testing framework for LLM Plugins
Author: shrikant
Author-email: shrikant.pm14@gmail.com
Requires-Python: >=3.9,<4.0
Classifier: Programming Language :: Python :: 3
Classifier: Programming Language :: Python :: 3.9
Classifier: Programming Language :: Python :: 3.10
Classifier: Programming Language :: Python :: 3.11
Requires-Dist: jinja2 (>=3.1.2,<4.0.0)
Requires-Dist: openplugin (>=0.0.14,<0.0.15)
Requires-Dist: pydantic (>=1.10.8,<2.0.0)
Requires-Dist: pydantic-yaml (>=0.11.2,<0.12.0)
Requires-Dist: pyyaml (>=6.0,<7.0)
Requires-Dist: requests (==2.29.0)
Requires-Dist: tqdm (>=4.65.0,<5.0.0)
Requires-Dist: typer[all] (>=0.9.0,<0.10.0)
